pydantic_settings_manager/__init__.py
pydantic_settings_manager/helpers.py
pydantic_settings_manager/manager.py
pydantic_settings_manager/py.typed
pydantic_settings_manager/types.py
pydantic_settings_manager/utils.py
pydantic_settings_manager-2.5.1.dist-info/METADATA
pydantic_settings_manager-2.5.1.dist-info/WHEEL
pydantic_settings_manager-2.5.1.dist-info/licenses/LICENSE
pydantic_settings_manager-2.5.1.dist-info/RECORD
