Metadata-Version: 2.4
Name: pydantic-settings-manager
Version: 2.5.1
Summary: A library for managing Pydantic settings objects
Project-URL: homepage, https://github.com/kiarina/pydantic-settings-manager
Project-URL: repository, https://github.com/kiarina/pydantic-settings-manager
Project-URL: documentation, https://github.com/kiarina/pydantic-settings-manager
Author-email: kiarina <kiarinadawa@gmail.com>
License: MIT
License-File: LICENSE
Keywords: configuration,pydantic,settings
Classifier: Development Status :: 4 - Beta
Classifier: Intended Audience :: Developers
Classifier: License :: OSI Approved :: MIT License
Classifier: Operating System :: OS Independent
Classifier: Programming Language :: Python :: 3
Classifier: Programming Language :: Python :: 3.12
Classifier: Programming Language :: Python :: 3.13
Classifier: Topic :: Software Development :: Libraries :: Python Modules
Requires-Python: >=3.12
Requires-Dist: pydantic-settings>=2.0.0
Requires-Dist: pydantic>=2.0.0
